tbnf/__init__.py
tbnf/__main__.py
tbnf/beforecodegen.py
tbnf/cli.py
tbnf/common.py
tbnf/config.py
tbnf/e.py
tbnf/macroresolve.py
tbnf/p.py
tbnf/parser.py
tbnf/parser_raw.py
tbnf/parser_utils.py
tbnf/prims.py
tbnf/r.py
tbnf/t.py
tbnf/typecheck.py
tbnf/unify.py
tbnf/backends/__init__.py
tbnf/backends/antlr.py
tbnf/backends/codeseg.py
tbnf/backends/csharp.py
tbnf/backends/doc.py
tbnf/backends/io_interface.py
tbnf/backends/lark.py
tbnf/backends/ocaml.py
tbnf-0.2.dist-info/LICENSE
tbnf-0.2.dist-info/METADATA
tbnf-0.2.dist-info/WHEEL
tbnf-0.2.dist-info/entry_points.txt
tbnf-0.2.dist-info/top_level.txt
tbnf-0.2.dist-info/RECORD
