Metadata-Version: 2.1
Name: tbnf
Version: 0.2
Summary: UNKNOWN
Home-page: https://github.com/thautwarm/.
Author: thautwarm
Author-email: twshere@outlook.com
License: mit
Platform: any
Classifier: Programming Language :: Python :: 3.6
Classifier: Programming Language :: Python :: 3.7
Classifier: Programming Language :: Python :: Implementation :: CPython
Requires-Python: >=3.6.0
Requires-Dist: wisepy2
Requires-Dist: typing-extensions
